cli/__init__.py
cli/command_router.py
cli/context.py
cli/main.py
cli/shell.py
cli/commands/__init__.py
cli/commands/alert_cmd.py
cli/commands/analyze_cmd.py
cli/commands/config_cmd.py
cli/commands/crawler_cmd.py
cli/commands/database_cmd.py
cli/commands/help_cmd.py
cli/commands/init_cmd.py
cli/commands/intelligence_cmd.py
cli/commands/report_cmd.py
cli/commands/safety_cmd.py
cli/commands/scheduler_cmd.py
cli/commands/search_cmd.py
cli/commands/view_cmd.py
crawlers/__init__.py
crawlers/base_crawler.py
crawlers/discord_crawler.py
crawlers/reddit_crawler.py
crawlers/steam_crawler.py
crawlers/steam_discussion_crawler.py
database/__init__.py
database/db_bridge.py
database/db_models.py
database/db_query_utils.py
database/db_session.py
gamedev_feedback_agent-0.1.0a4.dist-info/licenses/LICENSE
intelligence/__init__.py
intelligence/alert.py
intelligence/coverage.py
intelligence/embedding.py
intelligence/intelligence_config.py
intelligence/language.py
intelligence/priority_score.py
intelligence/process.py
intelligence/report.py
intelligence/safety.py
intelligence/sentiment.py
intelligence/providers/__init__.py
intelligence/providers/base_provider.py
intelligence/providers/ollama_provider.py
intelligence/providers/openai_provider.py
scheduler/__init__.py
scheduler/engine.py
scheduler/engine_utils.py
scheduler/job_config.py
scheduler/jobs.py
gamedev_feedback_agent-0.1.0a4.dist-info/METADATA
gamedev_feedback_agent-0.1.0a4.dist-info/WHEEL
gamedev_feedback_agent-0.1.0a4.dist-info/entry_points.txt
gamedev_feedback_agent-0.1.0a4.dist-info/top_level.txt
gamedev_feedback_agent-0.1.0a4.dist-info/RECORD
