Metadata-Version: 2.4
Name: gamedev-feedback-agent
Version: 0.1.0a4
Summary: Game Developer Community Feedback Agent CLI Tool
Author: VChahaha
License: MIT
Classifier: Development Status :: 3 - Alpha
Classifier: Intended Audience :: Developers
Classifier: Programming Language :: Python :: 3
Classifier: License :: OSI Approved :: MIT License
Requires-Python: >=3.8
License-File: LICENSE
Requires-Dist: aiohappyeyeballs==2.6.1
Requires-Dist: aiohttp==3.12.13
Requires-Dist: aiosignal==1.3.2
Requires-Dist: annotated-types==0.7.0
Requires-Dist: anyio==4.9.0
Requires-Dist: APScheduler==3.11.0
Requires-Dist: attrs==25.3.0
Requires-Dist: beautifulsoup4==4.13.4
Requires-Dist: certifi==2025.4.26
Requires-Dist: charset-normalizer==3.4.2
Requires-Dist: colorama==0.4.6
Requires-Dist: coverage==7.9.1
Requires-Dist: discord.py==2.5.2
Requires-Dist: distro==1.9.0
Requires-Dist: frozenlist==1.7.0
Requires-Dist: greenlet==3.2.3
Requires-Dist: h11==0.16.0
Requires-Dist: httpcore==1.0.9
Requires-Dist: httpx==0.28.1
Requires-Dist: idna==3.10
Requires-Dist: iniconfig==2.1.0
Requires-Dist: jiter==0.10.0
Requires-Dist: langdetect==1.0.9
Requires-Dist: markdown-it-py==3.0.0
Requires-Dist: mdurl==0.1.2
Requires-Dist: multidict==6.4.4
Requires-Dist: numpy==2.3.1
Requires-Dist: openai==1.93.0
Requires-Dist: packaging==25.0
Requires-Dist: pgvector==0.4.1
Requires-Dist: playwright==1.52.0
Requires-Dist: pluggy==1.6.0
Requires-Dist: praw==7.8.1
Requires-Dist: prawcore==2.4.0
Requires-Dist: propcache==0.3.2
Requires-Dist: psutil==7.0.0
Requires-Dist: psycopg2-binary==2.9.10
Requires-Dist: pydantic==2.11.7
Requires-Dist: pydantic_core==2.33.2
Requires-Dist: pyee==13.0.0
Requires-Dist: Pygments==2.19.2
Requires-Dist: pyreadline3==3.5.4
Requires-Dist: pytest==8.4.1
Requires-Dist: pytest-asyncio==1.0.0
Requires-Dist: pytest-cov==6.2.1
Requires-Dist: python-dotenv==1.1.0
Requires-Dist: pytz==2025.2
Requires-Dist: requests==2.32.4
Requires-Dist: rich==14.0.0
Requires-Dist: six==1.17.0
Requires-Dist: sniffio==1.3.1
Requires-Dist: soupsieve==2.7
Requires-Dist: SQLAlchemy==2.0.41
Requires-Dist: tqdm==4.67.1
Requires-Dist: typing-inspection==0.4.1
Requires-Dist: typing_extensions==4.14.0
Requires-Dist: tzdata==2025.2
Requires-Dist: tzlocal==5.3.1
Requires-Dist: update-checker==0.18.0
Requires-Dist: urllib3==2.4.0
Requires-Dist: websocket-client==1.8.0
Requires-Dist: yarl==1.20.1
Dynamic: author
Dynamic: classifier
Dynamic: description
Dynamic: description-content-type
Dynamic: license
Dynamic: license-file
Dynamic: requires-dist
Dynamic: requires-python
Dynamic: summary
